flask_factory/__init__.py
flask_factory/factory.py
flask_factory/initializer.py
flask_factory/utils.py
Flask_Factory-0.1.0dev.dist-info/DESCRIPTION.rst
Flask_Factory-0.1.0dev.dist-info/METADATA
Flask_Factory-0.1.0dev.dist-info/metadata.json
Flask_Factory-0.1.0dev.dist-info/RECORD
Flask_Factory-0.1.0dev.dist-info/top_level.txt
Flask_Factory-0.1.0dev.dist-info/WHEEL
Flask_Factory-0.1.0dev.dist-info/zip-safe
